iching_divination/__init__.py
iching_divination/divine.py
iching_divination-1.0.0.dist-info/METADATA
iching_divination-1.0.0.dist-info/WHEEL
iching_divination-1.0.0.dist-info/entry_points.txt
iching_divination-1.0.0.dist-info/licenses/LICENSE
iching_divination-1.0.0.dist-info/RECORD
