Metadata-Version: 2.4
Name: iching-divination
Version: 1.0.0
Summary: 易经解卦 - Three-Coin IChing Divination Calculator
Project-URL: Homepage, https://github.com/leether/iching-divination
Project-URL: Repository, https://github.com/leether/iching-divination
Project-URL: Issues, https://github.com/leether/iching-divination/issues
Author-email: leether <your.email@example.com>
License: MIT
License-File: LICENSE
Keywords: divination,iching,三硬币,易经,起卦
Classifier: Development Status :: 4 - Beta
Classifier: Intended Audience :: Developers
Classifier: Intended Audience :: End Users/Desktop
Classifier: License :: OSI Approved :: MIT License
Classifier: Programming Language :: Python :: 3
Classifier: Programming Language :: Python :: 3.8
Classifier: Programming Language :: Python :: 3.9
Classifier: Programming Language :: Python :: 3.10
Classifier: Programming Language :: Python :: 3.11
Classifier: Programming Language :: Python :: 3.12
Classifier: Topic :: Religion
Classifier: Topic :: Utilities
Requires-Python: >=3.8
Provides-Extra: dev
Requires-Dist: mypy>=1.0; extra == 'dev'
Requires-Dist: pytest-cov>=4.0; extra == 'dev'
Requires-Dist: pytest>=7.0; extra == 'dev'
